ufh/__init__.py
ufh/ufhUtils.py
ufh-1.0.1.dist-info/LICENSE
ufh-1.0.1.dist-info/METADATA
ufh-1.0.1.dist-info/WHEEL
ufh-1.0.1.dist-info/top_level.txt
ufh-1.0.1.dist-info/RECORD
